RsSmcv/RsSmcv.py
RsSmcv/__init__.py
RsSmcv/enums.py
RsSmcv/repcap.py
RsSmcv/CustomFiles/__init__.py
RsSmcv/CustomFiles/arb_files.py
RsSmcv/CustomFiles/digital_modulation.py
RsSmcv/CustomFiles/events.py
RsSmcv/CustomFiles/utilities.py
RsSmcv/Implementations/FormatPy.py
RsSmcv/Implementations/Kboard.py
RsSmcv/Implementations/Memory.py
RsSmcv/Implementations/Unit.py
RsSmcv/Implementations/__init__.py
RsSmcv/Implementations/Calibration/Bbin.py
RsSmcv/Implementations/Calibration/FmOffset.py
RsSmcv/Implementations/Calibration/Frequency.py
RsSmcv/Implementations/Calibration/LfOutput.py
RsSmcv/Implementations/Calibration/__init__.py
RsSmcv/Implementations/Calibration/All/Measure.py
RsSmcv/Implementations/Calibration/All/__init__.py
RsSmcv/Implementations/Calibration/Data/Factory.py
RsSmcv/Implementations/Calibration/Data/__init__.py
RsSmcv/Implementations/Calibration/Data/Update/__init__.py
RsSmcv/Implementations/Calibration/Data/Update/Level/Force.py
RsSmcv/Implementations/Calibration/Data/Update/Level/__init__.py
RsSmcv/Implementations/Calibration/Delay/Shutdown.py
RsSmcv/Implementations/Calibration/Delay/__init__.py
RsSmcv/Implementations/Calibration/IqModulator/Bband.py
RsSmcv/Implementations/Calibration/IqModulator/IqModulator.py
RsSmcv/Implementations/Calibration/IqModulator/__init__.py
RsSmcv/Implementations/Calibration/Level/Attenuator.py
RsSmcv/Implementations/Calibration/Level/Haccuracy.py
RsSmcv/Implementations/Calibration/Level/Measure.py
RsSmcv/Implementations/Calibration/Level/__init__.py
RsSmcv/Implementations/Calibration/Roscillator/Data.py
RsSmcv/Implementations/Calibration/Roscillator/Store.py
RsSmcv/Implementations/Calibration/Roscillator/__init__.py
RsSmcv/Implementations/Clock/InputPy.py
RsSmcv/Implementations/Clock/Output.py
RsSmcv/Implementations/Clock/Sync.py
RsSmcv/Implementations/Clock/__init__.py
RsSmcv/Implementations/Connector/RefLo.py
RsSmcv/Implementations/Connector/__init__.py
RsSmcv/Implementations/Connector/User/Omode.py
RsSmcv-5.20.44.dist-info/METADATA
RsSmcv-5.20.44.dist-info/WHEEL
RsSmcv-5.20.44.dist-info/top_level.txt
RsSmcv-5.20.44.dist-info/RECORD
